nvidia_pytriton.libs/libcudart-a647c843.so.12.6.77
nvidia_pytriton.libs/libkeyutils-a2c33366.so.1.9
nvidia_pytriton.libs/libarchive-114a4afe.so.13.6.0
nvidia_pytriton.libs/libnghttp2-32f7b207.so.14.20.1
nvidia_pytriton.libs/librtmp-bb308cf9.so.1
nvidia_pytriton.libs/libidn2-9e252f7b.so.0.3.7
nvidia_pytriton.libs/libbrotlicommon-1dbb5417.so.1.0.9
nvidia_pytriton.libs/libnettle-18a17fdf.so.8.4
nvidia_pytriton.libs/libxml2-f2ccccaa.so.2.9.13
nvidia_pytriton.libs/libdcgm-1c0f48fb.so.3.2.6
nvidia_pytriton.libs/libffi-b0c75d5a.so.8.1.0
nvidia_pytriton.libs/liblber-2-2d796b02.5.so.0.1.13
nvidia_pytriton.libs/libkrb5support-6a1c6571.so.0.1
nvidia_pytriton.libs/libldap-2-ce4b837b.5.so.0.1.13
nvidia_pytriton.libs/libk5crypto-87eac978.so.3.1
nvidia_pytriton.libs/liblz4-72a50edc.so.1.9.3
nvidia_pytriton.libs/libbz2-4bb4d93f.so.1.0.4
nvidia_pytriton.libs/libicuuc-6ab53856.so.70.1
nvidia_pytriton.libs/libcurl-204fd13e.so.4.7.0
nvidia_pytriton.libs/libtasn1-199753d2.so.6.6.2
nvidia_pytriton.libs/libgssapi_krb5-415a118c.so.2.2
nvidia_pytriton.libs/libicudata-727b7186.so.70.1
nvidia_pytriton.libs/libnuma-acd112e5.so.1.0.0
nvidia_pytriton.libs/libssl-b2e358a4.so.3
nvidia_pytriton.libs/libbrotlidec-eeabf6c1.so.1.0.9
nvidia_pytriton.libs/libtritonserver-035d00ec.so
nvidia_pytriton.libs/libb64-6d433260.so.0d
nvidia_pytriton.libs/libcrypto-e7f5e30d.so.3
nvidia_pytriton.libs/libp11-kit-a3e9dd2e.so.0.3.0
nvidia_pytriton.libs/liblzma-3da8981d.so.5.2.5
nvidia_pytriton.libs/libhogweed-3b521256.so.6.4
nvidia_pytriton.libs/libgmp-6d289461.so.10.4.1
nvidia_pytriton.libs/libzstd-a1561916.so.1.4.8
nvidia_pytriton.libs/libgnutls-4d08f6cb.so.30.31.0
nvidia_pytriton.libs/libsasl2-293f8b1f.so.2.0.25
nvidia_pytriton.libs/libpsl-681c76cd.so.5.3.2
nvidia_pytriton.libs/libssh-11e4eecd.so.4.8.7
nvidia_pytriton.libs/libacl-60509bc0.so.1.1.2301
nvidia_pytriton.libs/libcom_err-d1a4ee52.so.2.1
nvidia_pytriton.libs/libpython3-931631c3.13.so.1.0
nvidia_pytriton-0.7.0.dist-info/METADATA
nvidia_pytriton-0.7.0.dist-info/entry_points.txt
nvidia_pytriton-0.7.0.dist-info/WHEEL
nvidia_pytriton-0.7.0.dist-info/top_level.txt
nvidia_pytriton-0.7.0.dist-info/RECORD
nvidia_pytriton-0.7.0.dist-info/LICENSE
