Metadata-Version: 2.1
Name: nvidia-pytriton
Version: 0.7.0
Summary: PyTriton - Flask/FastAPI-like interface to simplify Triton's deployment in Python environments.
License: Apache 2.0
Project-URL: Documentation, https://triton-inference-server.github.io/pytriton
Project-URL: Source, https://github.com/triton-inference-server/pytriton
Project-URL: Tracker, https://github.com/triton-inference-server/pytriton/issues
Classifier: Development Status :: 3 - Alpha
Classifier: Intended Audience :: Science/Research
Classifier: Intended Audience :: Developers
Classifier: Topic :: Software Development
Classifier: Topic :: Scientific/Engineering
Classifier: Programming Language :: Python
Classifier: Programming Language :: Python :: 3
Classifier: Programming Language :: Python :: 3.8
Classifier: Programming Language :: Python :: 3.9
Classifier: Programming Language :: Python :: 3.10
Classifier: Programming Language :: Python :: 3.11
Classifier: Programming Language :: Python :: 3.12
Classifier: Operating System :: Unix
Requires-Python: <4,>=3.8
License-File: LICENSE
Requires-Dist: numpy<2.0.0,>=1.21
Requires-Dist: protobuf>=3.7
Requires-Dist: pyzmq>=23.0
Requires-Dist: sh>=1.14
Requires-Dist: tritonclient[grpc,http]~=2.50
Requires-Dist: grpcio>=1.64.3
Requires-Dist: typing-inspect>=0.6.0
Requires-Dist: wrapt>=1.11
Requires-Dist: typer>=0.9.0
Requires-Dist: importlib-metadata>=7.0.1
Provides-Extra: dev
Requires-Dist: nvidia-pytriton[test]; extra == "dev"
Requires-Dist: nvidia-pytriton[doc]; extra == "dev"
Requires-Dist: build<1.0.0,>=0.8; extra == "dev"
Requires-Dist: ipython>=8.12; extra == "dev"
Requires-Dist: packaging~=24.0; extra == "dev"
Requires-Dist: pudb>=2024.1; extra == "dev"
Requires-Dist: pip>=24.0; extra == "dev"
Requires-Dist: ruff>=0.3.0; extra == "dev"
Requires-Dist: twine>=5.0; extra == "dev"
Provides-Extra: doc
Requires-Dist: GitPython>=3.1; extra == "doc"
Requires-Dist: mike>=2.0.0; extra == "doc"
Requires-Dist: mkdocs-htmlproofer-plugin>=1.1; extra == "doc"
Requires-Dist: mkdocs-material>=9.5; extra == "doc"
Requires-Dist: mkdocstrings[python]<0.28.3; extra == "doc"
Requires-Dist: mkdocstrings-python>=1.8; extra == "doc"
Requires-Dist: mkdocs-mermaid2-plugin>=1.2.1; extra == "doc"
Provides-Extra: test
Requires-Dist: pytest~=8.1.1; extra == "test"
Requires-Dist: pytest-codeblocks~=0.16; extra == "test"
Requires-Dist: pytest-mock~=3.14; extra == "test"
Requires-Dist: pytest-timeout~=2.2; extra == "test"
Requires-Dist: pytest-asyncio~=0.23.5; extra == "test"
Requires-Dist: pytype!=2021.11.18,!=2022.2.17; extra == "test"
Requires-Dist: pre-commit>=3.5; extra == "test"
Requires-Dist: tox>=4.13; extra == "test"
Requires-Dist: tqdm>=4.64.1; extra == "test"
Requires-Dist: psutil~=5.9; extra == "test"
Requires-Dist: py-spy~=0.3; extra == "test"
Requires-Dist: opentelemetry-api; extra == "test"
Requires-Dist: opentelemetry-sdk; extra == "test"
Requires-Dist: opentelemetry-instrumentation-requests; extra == "test"
Requires-Dist: opentelemetry-exporter-otlp; extra == "test"
